{
    "meta": {
        "name": "TA-sandfly_devices",
        "displayName": "sandfly_devices",
        "version": "1.0.0",
        "restRoot": "TA_sandfly_devices",
        "schemaVersion": "0.0.3"
    },
    "pages": {
        "configuration": {
            "title": "Configuration",
            "description": "Set up your add-on",
            "tabs": [
                {
                    "name": "account",
                    "title": "Account",
                    "table": {
                        "header": [
                            {
                                "field": "name",
                                "label": "Account name"
                            },
                            {
                                "field": "hostname",
                                "label": "Hostname"
                            },
                            {
                                "field": "username",
                                "label": "Username"
                            },
                            {
                                "field": "ca_cert",
                                "label": "CA Certificate"
                            }
                        ],
                        "actions": [
                            "edit",
                            "delete",
                            "clone"
                        ]
                    },
                    "entity": [
                        {
                            "field": "name",
                            "label": "Account name",
                            "type": "text",
                            "required": true,
                            "help": "Enter a unique name for this account.",
                            "options": {
                                "placeholder": "Sandfly_01"
                            },
                            "validators": [
                                {
                                    "type": "string",
                                    "minLength": 1,
                                    "maxLength": 50,
                                    "errorMsg": "Length of Account name should be between 1 and 50"
                                },
                                {
                                    "type": "regex",
                                    "pattern": "^[a-zA-Z]\\w*$",
                                    "errorMsg": "Account name must start with a letter and followed by alphabetic letters, digits or underscores."
                                }
                            ]
                        },
                        {
                            "field": "username",
                            "label": "Username",
                            "type": "text",
                            "required": true,
                            "help": "Enter the username for this account.",
                            "options": {
                                "placeholder": "Enter the username here"
                            },
                            "validators": [
                                {
                                    "type": "string",
                                    "minLength": 1,
                                    "maxLength": 200,
                                    "errorMsg": "Length of username should be between 1 and 200"
                                }
                            ]
                        },
                        {
                            "field": "password",
                            "label": "Password",
                            "type": "text",
                            "encrypted": true,
                            "required": true,
                            "help": "Enter the password for this account.",
                            "validators": [
                                {
                                    "type": "string",
                                    "minLength": 1,
                                    "maxLength": 8192,
                                    "errorMsg": "Length of password should be between 1 and 8192"
                                }
                            ]
                        },
                        {
                            "field": "hostname",
                            "label": "Hostname",
                            "type": "text",
                            "required": true,
                            "help": "Enter the FQDN/IP for this account.",
                            "options": {
                                "placeholder": "sandfly1.example.com"
                            },
                            "validators": [
                                {
                                    "type": "string",
                                    "minLength": 1,
                                    "maxLength": 200,
                                    "errorMsg": "Length of hostname should be between 1 and 200"
                                }
                            ]
                        },
                        {
                            "field": "ca_cert",
                            "label": "CA Certificate",
                            "type": "text",
                            "required": false,
                            "help": "Name and Path of CA cert relative to $SPLUNK_HOME/etc/auth, the local directory of this app, or an absolute path.",
                            "options": {
                                "placeholder": "mycerts/ca-bundle.pem"
                            },
                            "validators": [
                                {
                                    "type": "string",
                                    "minLength": 1,
                                    "maxLength": 200,
                                    "errorMsg": "Length of certificate should be between 1 and 200"
                                }
                            ]
                        },
                        {
                            "field": "verify_cert",
                            "label": "Verify Certificate",
                            "type": "checkbox",
                            "required": false,
                            "help": "Verify certificate (default true)",
                            "defaultValue": true
                        }
                    ]
                },
                {
                    "name": "proxy",
                    "title": "Proxy",
                    "entity": [
                        {
                            "field": "proxy_enabled",
                            "label": "Enable",
                            "type": "checkbox"
                        },
                        {
                            "field": "proxy_type",
                            "label": "Proxy Type",
                            "type": "singleSelect",
                            "options": {
                                "disableSearch": true,
                                "autoCompleteFields": [
                                    {
                                        "label": "http",
                                        "value": "http"
                                    },
                                    {
                                        "label": "socks4",
                                        "value": "socks4"
                                    },
                                    {
                                        "label": "socks5",
                                        "value": "socks5"
                                    }
                                ]
                            },
                            "defaultValue": "http"
                        },
                        {
                            "field": "proxy_url",
                            "label": "Host",
                            "type": "text",
                            "validators": [
                                {
                                    "type": "string",
                                    "minLength": 0,
                                    "maxLength": 4096,
                                    "errorMsg": "Max host length is 4096"
                                }
                            ]
                        },
                        {
                            "field": "proxy_port",
                            "label": "Port",
                            "type": "text",
                            "validators": [
                                {
                                    "type": "number",
                                    "range": [
                                        1,
                                        65535
                                    ]
                                }
                            ]
                        },
                        {
                            "field": "proxy_username",
                            "label": "Username",
                            "type": "text",
                            "validators": [
                                {
                                    "type": "string",
                                    "minLength": 0,
                                    "maxLength": 50,
                                    "errorMsg": "Max length of username is 50"
                                }
                            ]
                        },
                        {
                            "field": "proxy_password",
                            "label": "Password",
                            "type": "text",
                            "encrypted": true,
                            "validators": [
                                {
                                    "type": "string",
                                    "minLength": 0,
                                    "maxLength": 8192,
                                    "errorMsg": "Max length of password is 8192"
                                }
                            ]
                        },
                        {
                            "field": "proxy_rdns",
                            "label": "Remote DNS resolution",
                            "type": "checkbox"
                        }
                    ],
                    "options": {
                        "saveValidator": "function(formData) { if(!formData.proxy_enabled || formData.proxy_enabled === '0') {return true; } if(!formData.proxy_url) { return 'Proxy Host can not be empty'; } if(!formData.proxy_port) { return 'Proxy Port can not be empty'; } return true; }"
                    }
                },
                {
                    "name": "logging",
                    "title": "Logging",
                    "entity": [
                        {
                            "field": "loglevel",
                            "label": "Log level",
                            "type": "singleSelect",
                            "options": {
                                "disableSearch": true,
                                "autoCompleteFields": [
                                    {
                                        "label": "DEBUG",
                                        "value": "DEBUG"
                                    },
                                    {
                                        "label": "INFO",
                                        "value": "INFO"
                                    },
                                    {
                                        "label": "WARNING",
                                        "value": "WARNING"
                                    },
                                    {
                                        "label": "ERROR",
                                        "value": "ERROR"
                                    },
                                    {
                                        "label": "CRITICAL",
                                        "value": "CRITICAL"
                                    }
                                ]
                            },
                            "defaultValue": "INFO"
                        }
                    ]
                }
            ]
        },
        "inputs": {
            "title": "Inputs",
            "description": "Manage your data inputs",
            "table": {
                "header": [
                    {
                        "field": "name",
                        "label": "Name"
                    },
                    {
                        "field": "global_account",
                        "label": "Global Account"
                    },
                    {
                        "field": "interval",
                        "label": "Interval"
                    },
                    {
                        "field": "index",
                        "label": "Index"
                    },
                    {
                        "field": "disabled",
                        "label": "Status"
                    }
                ],
                "moreInfo": [
                    {
                        "field": "name",
                        "label": "Name"
                    },
                    {
                        "field": "interval",
                        "label": "Interval"
                    },
                    {
                        "field": "index",
                        "label": "Index"
                    },
                    {
                        "field": "host_summary",
                        "label": "Host Summary"
                    },
                    {
                        "field": "disabled",
                        "label": "Disabled"
                    },
                    {
                        "field": "global_account",
                        "label": "Global Account"
                    }
                ],
                "actions": [
                    "edit",
                    "enable",
                    "delete",
                    "clone"
                ]
            },
            "services": [
                {
                    "name": "sandfly_devices",
                    "title": "Sandfly Devices",
                    "entity": [
                        {
                            "field": "name",
                            "label": "Name",
                            "type": "text",
                            "help": "Enter a unique name for the data input (no spaces).",
                            "options": {
                                "placeholder": "Sandfly1_Devices"
                            },
                            "required": true,
                            "validators": [
                                {
                                    "type": "regex",
                                    "pattern": "^[a-zA-Z]\\w*$",
                                    "errorMsg": "Input Name must start with a letter and followed by alphabetic letters, digits or underscores."
                                },
                                {
                                    "type": "string",
                                    "minLength": 1,
                                    "maxLength": 100,
                                    "errorMsg": "Length of input name should be between 1 and 100"
                                }
                            ]
                        },
                        {
                            "field": "interval",
                            "label": "Interval",
                            "type": "text",
                            "required": true,
                            "help": "Time interval of input in seconds, minimum 300s (5 minutes) or a valid cron schedule.",
                            "options": {
                                "placeholder": "4 * * * *"
                            },
                            "validators": [
                                {
                                    "type": "regex",
                                    "pattern": "(?:(?:^[3-9][0-9][0-9]$|^[1-9][0-9][0-9][0-9]\\d*$)|(?:^\\S+(?: \\S+){4}))",
                                    "errorMsg": "Interval must be an integer larger than 300 or a valid cron schedule."
                                }
                            ]
                        },
                        {
                            "field": "index",
                            "label": "Index",
                            "type": "singleSelect",
                            "defaultValue": "default",
                            "options": {
                                "endpointUrl": "data/indexes",
                                "createSearchChoice": true,
                                "denyList": "^_.*$"
                            },
                            "required": true,
                            "validators": [
                                {
                                    "type": "string",
                                    "minLength": 1,
                                    "maxLength": 80,
                                    "errorMsg": "Length of index name should be between 1 and 80."
                                }
                            ]
                        },
                        {
                            "field": "global_account",
                            "label": "Global Account",
                            "help": "",
                            "required": true,
                            "type": "singleSelect",
                            "options": {
                                "referenceName": "account",
                                "placeholder": "Select the Global Account to use."
                            }
                        },
                        {
                            "field": "host_summary",
                            "label": "Host Summary",
                            "type": "checkbox",
                            "required": false,
                            "help": "If checked, returns flattened summary view of all hosts (default checked).",
                            "defaultValue": true
                        }
                    ]
                }
            ]
        }
    }
}
